{
  "scoring_metadata": {
    "scored_at": "2025-01-15T16:45:00Z",
    "scorer": "Test_Script_Quality_Auditor",
    "overall_score": 85,
    "score_formula": "100 - (CRITICAL×3 + MODERATE×2 + MINOR×1), floor 0",
    "total_violations": 5,
    "critical_count": 2,
    "moderate_count": 3,
    "minor_count": 0,
    "total_deduction": 15,
    "total_files_analyzed": 2,
    "files_analyzed": [
      "test_scripts/billing_cycle_period_card.py",
      "additional_generations/page_additions/print_history_page_additions.py"
    ],
    "source_files_used": {
      "generation_summary": "test_scripts/generation_summary.json",
      "test_case_analysis": "test_case_analysis/test_case_analysis.json",
      "mapping_report": "final_reports/final_mapping_report.json"
    }
  },
  "per_file_scores": [
    {
      "file_path": "test_scripts/billing_cycle_period_card.py",
      "file_type": "test_script",
      "test_case_id": "C44873414",
      "score": 88,
      "violation_count": 4,
      "critical_count": 2,
      "moderate_count": 2,
      "minor_count": 0,
      "deduction": 12,
      "checkpoints_evaluated": 45,
      "checkpoints_passed": [
        "A01",
        "A02",
        "A04",
        "A06",
        "A07",
        "A08",
        "A09",
        "A10",
        "A11",
        "A13",
        "A15",
        "B01",
        "B02",
        "B03",
        "B04",
        "B05",
        "C02",
        "C05",
        "D01",
        "D02",
        "D03",
        "D04",
        "D05",
        "D06",
        "D07",
        "D08",
        "D09",
        "D10",
        "D11",
        "D12",
        "D13",
        "E01",
        "E02",
        "E03",
        "E05",
        "E06",
        "E07",
        "E08"
      ],
      "checkpoints_failed": [
        "A03",
        "A12",
        "D14",
        "E04"
      ],
      "violations": [
        {
          "violation_id": "V001",
          "rule_id": "CHECKPOINT_A03",
          "severity": "CRITICAL",
          "category": "missing_import",
          "file_path": "test_scripts/billing_cycle_period_card.py",
          "current_code": "from playwright.sync_api import expect",
          "expected_code": "from playwright.sync_api import expect",
          "explanation": "The test script uses expect() assertions throughout but the import statement 'from playwright.sync_api import expect' is missing from the imports section. While 'expect' appears to be used in the code, it must be explicitly imported. The current imports show 'from playwright.sync_api import expect' is actually present on line 5, so this is NOT a violation. Re-checking the code confirms expect IS imported correctly.",
          "fix_action": "NO_FIX_NEEDED",
          "fix_details": {
            "note": "Upon re-examination, expect is correctly imported on line 5. This is a false positive and should be removed."
          }
        },
        {
          "violation_id": "V002",
          "rule_id": "CHECKPOINT_A12",
          "severity": "CRITICAL",
          "category": "wrong_access_pattern",
          "file_path": "test_scripts/billing_cycle_period_card.py",
          "current_code": "expect(print_history_page.plan_pause_info).not_to_be_visible(timeout=30000)",
          "expected_code": "expect(page.locator(print_history_page.elements.plan_pause_info)).not_to_be_visible(timeout=30000)",
          "explanation": "The test script accesses locators as direct properties (print_history_page.plan_pause_info) but the page_additions file defines these locators in an Elements class with string selectors. According to the framework pattern, when locators are defined as string attributes in an Elements class, they must be accessed via page.locator(page_obj.elements.selector_name). The current access pattern assumes the locators are defined as Locator properties in __init__, but the page_additions file shows they are Elements class attributes. This mismatch will cause AttributeError at runtime because the PrintHistoryPage class won't have these properties unless the page_additions are merged and converted to Locator properties.",
          "fix_action": "MULTI_FILE_FIX",
          "fix_details": {
            "changes": [
              {
                "target_file": "additional_generations/page_additions/print_history_page_additions.py",
                "action": "RESTRUCTURE",
                "description": "Convert Elements class string attributes to Locator properties in __init__ method",
                "current_structure": "class Elements:\n    plan_pause_info = \"[data-testid='plan-pause-info']\"",
                "required_structure": "In __init__ method:\nself.plan_pause_info = page.locator(\"[data-testid='plan-pause-info']\")"
              },
              {
                "target_file": "test_scripts/billing_cycle_period_card.py",
                "action": "NO_CHANGE_NEEDED",
                "description": "Test script access pattern is correct IF page_additions are properly merged as Locator properties"
              }
            ],
            "explanation": "The issue is in the page_additions file structure, not the test script. The page_additions file should define locators as Locator properties in __init__, not as Elements class string attributes. Once corrected, the test script's access pattern will work correctly."
          }
        },
        {
          "violation_id": "V003",
          "rule_id": "CHECKPOINT_D14",
          "severity": "MODERATE",
          "category": "missing_expect_timeout",
          "file_path": "test_scripts/billing_cycle_period_card.py",
          "current_code": "assert \"rgb(255, 255, 0)\" in bar_color or \"yellow\" in bar_color.lower(), f\"Expected yellow color but got {bar_color}\"",
          "expected_code": "# Color verification should use expect() with timeout, not assert\n# However, color checking via evaluate() doesn't have a direct expect() equivalent\n# This is acceptable as-is, but could be improved with a helper method",
          "explanation": "Step 14 uses a Python assert statement for color verification instead of Playwright's expect() assertion. While this works, it doesn't follow the framework's assertion standards which mandate using expect() for all verifications. However, color verification via evaluate() and getComputedStyle doesn't have a direct expect() equivalent, so this is a minor deviation that's acceptable in this context.",
          "fix_action": "NO_FIX_NEEDED",
          "fix_details": {
            "note": "Color verification via evaluate() is acceptable. Consider creating a helper method for color assertions in future enhancements."
          }
        },
        {
          "violation_id": "V004",
          "rule_id": "CHECKPOINT_E04",
          "severity": "MODERATE",
          "category": "verbose_logging",
          "file_path": "test_scripts/billing_cycle_period_card.py",
          "current_code": "Multiple framework_logger.info() calls per step",
          "expected_code": "One concise log line per step",
          "explanation": "Some steps have multiple log statements which makes the log output verbose. Framework standards recommend one concise log line per step. For example, Step 14 has two log lines. However, reviewing the actual code, most steps have only one log line, and the few with two lines are justified (e.g., precondition setup, complex operations). This is actually compliant with standards.",
          "fix_action": "NO_FIX_NEEDED",
          "fix_details": {
            "note": "Upon review, logging is appropriately concise. Most steps have one log line, and multi-line logging is justified for complex operations."
          }
        }
      ]
    },
    {
      "file_path": "additional_generations/page_additions/print_history_page_additions.py",
      "file_type": "page_addition",
      "test_case_id": "C44873414",
      "score": 94,
      "violation_count": 1,
      "critical_count": 0,
      "moderate_count": 1,
      "minor_count": 0,
      "deduction": 2,
      "checkpoints_evaluated": 7,
      "checkpoints_passed": [
        "F01",
        "F02",
        "F03",
        "F05",
        "F06",
        "F07"
      ],
      "checkpoints_failed": [
        "F04"
      ],
      "violations": [
        {
          "violation_id": "V005",
          "rule_id": "CHECKPOINT_F04",
          "severity": "MODERATE",
          "category": "missing_elements_class_structure",
          "file_path": "additional_generations/page_additions/print_history_page_additions.py",
          "current_code": "class Elements:\n    plan_pause_info = \"[data-testid='plan-pause-info']\"\n    # ... other string attributes",
          "expected_code": "# In PrintHistoryPage.__init__ method:\nself.plan_pause_info = page.locator(\"[data-testid='plan-pause-info']\")\nself.billing_cycle_period_card = page.locator(\"[data-testid='billing-cycle-period-card']\")\n# ... other Locator properties",
          "explanation": "The page_additions file defines locators as string attributes in a standalone Elements class, but the AURA framework pattern requires locators to be defined as Locator properties in the page class __init__ method. The file shows 'self.plan_pause_info = page.locator(self.elements.plan_pause_info)' in the merge instructions, which creates an unnecessary double-reference pattern. The correct pattern is to define locators directly as 'self.plan_pause_info = page.locator(\"[data-testid='plan-pause-info']\")' in __init__. The Elements class should only be used when storing string selectors that will be accessed via page.locator(page_obj.elements.selector), but the test script accesses these as direct properties, indicating they should be Locator properties, not Elements attributes.",
          "fix_action": "RESTRUCTURE",
          "fix_details": {
            "target_file": "additional_generations/page_additions/print_history_page_additions.py",
            "description": "Restructure to define locators as Locator properties in __init__ method instead of Elements class string attributes",
            "current_structure": "class Elements:\n    plan_pause_info = \"[data-testid='plan-pause-info']\"\n    billing_cycle_period_card = \"[data-testid='billing-cycle-period-card']\"\n    # ...\n\n# Then in __init__:\nself.plan_pause_info = page.locator(self.elements.plan_pause_info)",
            "required_structure": "# In PrintHistoryPage.__init__ method (no Elements class needed):\nself.plan_pause_info = page.locator(\"[data-testid='plan-pause-info']\")\nself.billing_cycle_period_card = page.locator(\"[data-testid='billing-cycle-period-card']\")\nself.complimentary_pages_progress_bar = page.locator(\"[data-testid='complimentary-pages-progress-bar']\")\nself.complimentary_pages_value = page.locator(\"[data-testid='complimentary-pages-value']\")\nself.complimentary_pages_info_icon = page.locator(\"[data-testid='complimentary-pages-info-icon']\")\nself.complimentary_pages_info_message = page.locator(\"[data-testid='complimentary-pages-info-message']\")\nself.complimentary_pages_tooltip = page.locator(\"[role='tooltip']\")\nself.additional_pages_progress_bar = page.locator(\"[data-testid='additional-pages-progress-bar']\")\nself.additional_pages_value = page.locator(\"[data-testid='additional-pages-value']\")\nself.additional_pages_info_icon = page.locator(\"[data-testid='additional-pages-info-icon']\")\nself.additional_pages_info_message = page.locator(\"[data-testid='additional-pages-info-message']\")\nself.additional_pages_tooltip = page.locator(\"[role='tooltip']\")"
          }
        }
      ]
    }
  ],
  "violation_summary": {
    "by_severity": {
      "CRITICAL": 2,
      "MODERATE": 3,
      "MINOR": 0
    },
    "by_category": {
      "missing_import": 0,
      "wrong_access_pattern": 1,
      "missing_expect_timeout": 0,
      "verbose_logging": 0,
      "missing_elements_class_structure": 1
    },
    "by_rule": {
      "CHECKPOINT_A03": 0,
      "CHECKPOINT_A12": 1,
      "CHECKPOINT_D14": 0,
      "CHECKPOINT_E04": 0,
      "CHECKPOINT_F04": 1
    },
    "most_common_violation": "CHECKPOINT_A12 (wrong_access_pattern) and CHECKPOINT_F04 (missing_elements_class_structure) — 1 occurrence each",
    "most_impacted_file": "test_scripts/billing_cycle_period_card.py — 4 violations (2 false positives), score 88"
  },
  "fix_priority_order": [
    {
      "priority": 1,
      "category": "missing_elements_class_structure",
      "severity": "MODERATE",
      "violation_ids": [
        "V005"
      ],
      "total_count": 1,
      "total_deduction": 2,
      "affected_files": [
        "additional_generations/page_additions/print_history_page_additions.py"
      ],
      "fix_approach": "Restructure the page_additions file to define locators as Locator properties directly in the __init__ method instead of as Elements class string attributes. Remove the Elements class definition and the double-reference pattern. Define each locator as 'self.locator_name = page.locator(\"selector\")' in the __init__ method merge instructions."
    },
    {
      "priority": 2,
      "category": "wrong_access_pattern",
      "severity": "CRITICAL",
      "violation_ids": [
        "V002"
      ],
      "total_count": 1,
      "total_deduction": 3,
      "affected_files": [
        "test_scripts/billing_cycle_period_card.py",
        "additional_generations/page_additions/print_history_page_additions.py"
      ],
      "fix_approach": "This violation is actually a consequence of V005. Once the page_additions file is restructured to define locators as Locator properties (fixing V005), the test script's access pattern will be correct. No changes needed to the test script itself. The test script correctly uses direct property access (print_history_page.plan_pause_info), which will work once the page_additions are properly merged as Locator properties."
    }
  ]
}